PyTaskbar/ProgressAPI.py
PyTaskbar/TaskbarLib.tlb
PyTaskbar/__init__.py
PyTaskbarProgress-0.0.8.dist-info/LICENSE
PyTaskbarProgress-0.0.8.dist-info/METADATA
PyTaskbarProgress-0.0.8.dist-info/WHEEL
PyTaskbarProgress-0.0.8.dist-info/top_level.txt
PyTaskbarProgress-0.0.8.dist-info/RECORD
