Metadata-Version: 2.1
Name: PyTaskbarProgress
Version: 0.0.8
Summary: The ultimate taskbar progress python package!
Home-page: https://github.com/somePythonProgrammer/PyTaskbar
Download-URL: https://github.com/somePythonProgrammer/PyTaskbar/archive/refs/tags/0.0.8.tar.gz
Author: somePythonProgrammer
Classifier: License :: OSI Approved :: MIT License
Classifier: Operating System :: Microsoft :: Windows :: Windows 10
Requires-Python: >=3.6
License-File: LICENSE
Requires-Dist: comtypes
Requires-Dist: pygetwindow
Requires-Dist: setuptools
